lazr.delegates-2.1.1-py3.13-nspkg.pth
lazr/delegates/__init__.py
lazr/delegates/_delegates.py
lazr/delegates/docs/CONTRIBUTING.rst
lazr/delegates/docs/NEWS.rst
lazr/delegates/docs/__init__.py
lazr/delegates/docs/conf.py
lazr/delegates/docs/index.rst
lazr/delegates/tests/__init__.py
lazr/delegates/tests/test_api.py
lazr/delegates/tests/test_docs.py
lazr/delegates/tests/test_passthrough.py
lazr.delegates-2.1.1.dist-info/COPYING.txt
lazr.delegates-2.1.1.dist-info/METADATA
lazr.delegates-2.1.1.dist-info/WHEEL
lazr.delegates-2.1.1.dist-info/namespace_packages.txt
lazr.delegates-2.1.1.dist-info/top_level.txt
lazr.delegates-2.1.1.dist-info/RECORD
